{
  "schema": {
    "name": "schema-std",
    "version": 1
  },
  "dependsOn": [
    "core:config",
    "core:change",
    "core:schema-format",
    "core:content-extraction",
    "core:spec-repository-port",
    "core:spec-lock"
  ],
  "implementation": [
    {
      "file": "core:src/application/use-cases/generate-spec-metadata.ts"
    },
    {
      "file": "core:src/domain/services/parse-metadata.ts",
      "symbols": [
        "specMetadataSchema",
        "strictSpecMetadataSchema",
        "permissiveSpecMetadataSchema",
        "SpecMetadata"
      ]
    }
  ]
}
